sqlsite/__init__.py
sqlsite/database.py
sqlsite/exists.py
sqlsite/handlers.py
sqlsite/request.py
sqlsite/responses.py
sqlsite/routing.py
sqlsite/sql.py
sqlsite/sqlar.py
sqlsite/wsgi.py
tests/__init__.py
tests/conftest.py
tests/test_database.py
tests/test_exists.py
tests/test_routing.py
tests/test_sql.py
tests/test_sqlar.py
tests/test_wsgi.py
tests/utils.py
tests/handlers/__init__.py
tests/handlers/test_json.py
tests/handlers/test_redirect.py
tests/handlers/test_static.py
tests/handlers/test_template.py
sqlsite-0.0.3.dist-info/LICENSE
sqlsite-0.0.3.dist-info/METADATA
sqlsite-0.0.3.dist-info/WHEEL
sqlsite-0.0.3.dist-info/top_level.txt
sqlsite-0.0.3.dist-info/RECORD
