Metadata-Version: 2.1
Name: sqlsite
Version: 0.0.3
Summary: A tool for serving simple websites, JSON APIs and static files directly from a SQLite database.
Home-page: https://github.com/j4mie/sqlsite
Author: Jamie Matthews
Author-email: jamie@mtth.org
License: UNKNOWN
Platform: UNKNOWN
Classifier: Topic :: Internet :: WWW/HTTP
Classifier: Environment :: Web Environment
Classifier: Programming Language :: Python :: 3
Classifier: License :: Public Domain
Classifier: Operating System :: OS Independent
Requires-Python: >=3.7
Requires-Dist: apsw
Requires-Dist: jinja2
